Blocking_and_Nonblocking/blocking/blocking.v
module blocking (
    clk,
    rst_n,
    a_i,
    b_i,
    a_o,
    b_o
);

input clk;
input rst_n;
input a_i, b_i;
output a_o, b_o;
reg a, b;

assign a_o = a;
assign b_o = b;
always @(posedge clk or negedge rst_n) begin

    if (~rst_n) begin   //blocking寫法，所以a = a_i;b = b_i;會按照順序執行

        a = a_i;
        b = b_i;

    end
    else begin

        a = b;
        b = a;
        
    end
end
endmodule

BCD/BCD.v
module BCD(clk, rst);
input clk; //I clock in
input rst; //I asyn reset
output [3:0] Q_out; // O asyn Result
reg [3:0] Q_out;

initial begin
    Q_out = 4'b0000;    
end

always@ (posedge clk or posedge rst)
begin
    if (rst)
        Q_out = 0;
    else if (Q_out == 9)
        Q_out = 0;
    else
        Q_out++;
end
endmodule

BCD/BCD_tb.v
// `include "blocking.v"
`timescale 1ns/1ps
module BCD_tb;
reg clk_tb;
reg rst_tb;

initial begin
    clk_tb = 0;
    rst_tb = 0;
end

// clock process
always begin
    #10 clk_tb = ~clk_tb;
end

initial begin
    #30 rst_tb = 1'b0;
    #10 rst_tb = 1'b1;
    #5 rst_tb = 1'b0;
    #250 $finish;
end

initial begin
    $dumpfile("BCD.vcd");
    $dumpvars(0, BCD_tb);
end

BCD BCD_tb (
    .clk(clk_tb),
    .rst(rst_tb)
    );    
endmodule

BCD/BCD.vcd
$date
	Sun Sep 01 20:13:02 2024
$end
$version
	Icarus Verilog
$end
$timescale
	1ps
$end
$scope module BCD_tb $end
$scope module BCD_tb $end
$var wire 1 ! clk $end
$var wire 1 " rst $end
$var reg 4 # Q_out [3:0] $end
$upscope $end
$upscope $end
$enddefinitions $end
$comment Show the parameter values. $end
$dumpall
$end
#0
$dumpvars
b0 #
0"
0!
$end
#10000
b1 #
1!
#20000
0!
#30000
b10 #
1!
#40000
b0 #
0!
1"
#45000
0"
#50000
b1 #
1!
#60000
0!
#70000
b10 #
1!
#80000
0!
#90000
b11 #
1!
#100000
0!
#110000
b100 #
1!
#120000
0!
#130000
b101 #
1!
#140000
0!
#150000
b110 #
1!
#160000
0!
#170000
b111 #
1!
#180000
0!
#190000
b1000 #
1!
#200000
0!
#210000
b1001 #
1!
#220000
0!
#230000
b0 #
1!
#240000
0!
#250000
b1 #
1!
#260000
0!
#270000
b10 #
1!
#280000
0!
#290000
b11 #
1!
